{
  "train": [
    {
      "epoch": 1,
      "loss": 1.3880235221650865,
      "acc": 0.2485
    },
    {
      "epoch": 2,
      "loss": 1.3872051220091561,
      "acc": 0.2585
    },
    {
      "epoch": 3,
      "loss": 1.388419781412397,
      "acc": 0.24725
    },
    {
      "epoch": 4,
      "loss": 1.3892590810382177,
      "acc": 0.23575
    },
    {
      "epoch": 5,
      "loss": 1.3886073789899311,
      "acc": 0.25025
    }
  ],
  "val": [
    {
      "epoch": 1,
      "loss": 1.3868361234664917,
      "acc": 0.25259259263674416
    },
    {
      "epoch": 2,
      "loss": 1.3861851201337927,
      "acc": 0.2514814814814815
    },
    {
      "epoch": 3,
      "loss": 1.3863724694532507,
      "acc": 0.2579629630071146
    },
    {
      "epoch": 4,
      "loss": 1.387920044450199,
      "acc": 0.2474074074074074
    },
    {
      "epoch": 5,
      "loss": 1.3873623707715204,
      "acc": 0.24999999997792421
    }
  ]
}