{
  "train": [
    {
      "epoch": 1,
      "loss": 1.3874277637004853,
      "acc": 0.252
    },
    {
      "epoch": 2,
      "loss": 1.3864556488990785,
      "acc": 0.24565625
    },
    {
      "epoch": 3,
      "loss": 1.3863453245162964,
      "acc": 0.25009375
    },
    {
      "epoch": 4,
      "loss": 1.3821424853801727,
      "acc": 0.267625
    },
    {
      "epoch": 5,
      "loss": 1.3104106423854829,
      "acc": 0.38559375
    },
    {
      "epoch": 6,
      "loss": 1.2694776322841643,
      "acc": 0.44084375
    },
    {
      "epoch": 7,
      "loss": 1.1795323581695556,
      "acc": 0.53140625
    },
    {
      "epoch": 8,
      "loss": 1.169618819475174,
      "acc": 0.55925
    },
    {
      "epoch": 9,
      "loss": 1.127227002263069,
      "acc": 0.6066875
    }
  ],
  "val": [
    {
      "epoch": 1,
      "loss": 1.3869084666757023,
      "acc": 0.24351851851851852
    },
    {
      "epoch": 2,
      "loss": 1.3861903513179106,
      "acc": 0.25666666666666665
    },
    {
      "epoch": 3,
      "loss": 1.3861747615477618,
      "acc": 0.2696296296296296
    },
    {
      "epoch": 4,
      "loss": 1.3130516599206363,
      "acc": 0.39481481481481484
    },
    {
      "epoch": 5,
      "loss": 1.3640294271356919,
      "acc": 0.39037037037037037
    },
    {
      "epoch": 6,
      "loss": 0.970282659109901,
      "acc": 0.7688888888888888
    },
    {
      "epoch": 7,
      "loss": 1.225059168479022,
      "acc": 0.5416666666666666
    },
    {
      "epoch": 8,
      "loss": 1.2545008547165815,
      "acc": 0.5181481481481481
    },
    {
      "epoch": 9,
      "loss": 1.2601066701552448,
      "acc": 0.5627777777777778
    }
  ]
}